core/__init__.py
core/app.py
core/config.py
core/crypto.py
core/deps/__init__.py
core/deps/auth.py
core/deps/cache.py
core/deps/db.py
core/deps/http_client.py
core/excs.py
core/lifespan.py
core/lock.py
core/main.py
core/sentry.py
tiny_service_core-0.1.1.dist-info/WHEEL
tiny_service_core-0.1.1.dist-info/METADATA
tiny_service_core-0.1.1.dist-info/RECORD
