Metadata-Version: 2.3
Name: tiny-service-core
Version: 0.1.1
Summary: 🪐 Shared functionality for tiny microservices
Keywords: async,fastapi,microservice,core
Author: Aliaksei Urbanski
Author-email: Aliaksei Urbanski <aliaksei.urbanski@gmail.com>
License: MIT
Classifier: License :: OSI Approved :: MIT License
Classifier: Development Status :: 4 - Beta
Classifier: Environment :: Web Environment
Classifier: Framework :: AsyncIO
Classifier: Framework :: FastAPI
Classifier: Framework :: Pydantic
Classifier: Intended Audience :: Developers
Classifier: Operating System :: OS Independent
Classifier: Topic :: Internet
Classifier: Topic :: Internet :: WWW/HTTP
Classifier: Topic :: Internet :: WWW/HTTP :: HTTP Servers
Classifier: Topic :: Software Development
Classifier: Topic :: Software Development :: Libraries
Classifier: Topic :: Software Development :: Libraries :: Application Frameworks
Classifier: Topic :: Software Development :: Libraries :: Python Modules
Classifier: Typing :: Typed
Classifier: Programming Language :: Python
Classifier: Programming Language :: Python :: 3.12
Classifier: Programming Language :: Python :: 3.13
Classifier: Programming Language :: Python :: 3.14
Classifier: Programming Language :: Python :: Implementation :: CPython
Requires-Dist: fastapi
Requires-Dist: pydantic-settings
Requires-Dist: sentry-sdk[fastapi]
Requires-Dist: redis ; extra == 'cache'
Requires-Dist: alembic ; extra == 'db'
Requires-Dist: asyncpg ; extra == 'db'
Requires-Dist: sentry-sdk[asyncpg,sqlalchemy] ; extra == 'db'
Requires-Dist: sqlmodel ; extra == 'db'
Requires-Dist: fastapi[standard] ; extra == 'dev'
Requires-Dist: httpx ; extra == 'http-client'
Requires-Dist: sentry-sdk[httpx] ; extra == 'http-client'
Requires-Dist: python-multipart ; extra == 'multipart'
Maintainer: Aliaksei Urbanski
Maintainer-email: Aliaksei Urbanski <aliaksei.urbanski@gmail.com>
Requires-Python: >=3.12
Project-URL: Issues, https://github.com/Jamim/tiny-service-core/issues
Project-URL: Repository, https://github.com/Jamim/tiny-service-core
Provides-Extra: cache
Provides-Extra: db
Provides-Extra: dev
Provides-Extra: http-client
Provides-Extra: multipart
